[{"id": 1, "subject": "English", "topic": "Idioms and Phrases", "difficulty": "Easy"}, {"id": 2, "subject": "English", "topic": "Idioms and Phrases", "difficulty": "Easy"}, {"id": 3, "subject": "English", "topic": "Idioms and Phrases", "difficulty": "Easy"}, {"id": 4, "subject": "English", "topic": "Idioms and Phrases", "difficulty": "Easy"}, {"id": 5, "subject": "English", "topic": "Idioms and Phrases", "difficulty": "Easy"}, {"id": 6, "subject": "English", "topic": "Idioms and Phrases", "difficulty": "Easy"}, {"id": 7, "subject": "English", "topic": "Idioms and Phrases", "difficulty": "Easy"}, {"id": 8, "subject": "English", "topic": "Idioms and Phrases", "difficulty": "Medium"}, {"id": 9, "subject": "English", "topic": "Idioms and Phrases", "difficulty": "Medium"}]