[{"id": 1, "subject": "Economy", "topic": "National Income Accounting", "difficulty": "Medium"}, {"id": 2, "subject": "Economy", "topic": "Balance of Payments", "difficulty": "Medium"}, {"id": 3, "subject": "General Knowledge", "topic": "Indian Labour Laws", "difficulty": "Easy"}, {"id": 4, "subject": "Economy", "topic": "Public Finance", "difficulty": "Medium"}, {"id": 5, "subject": "Economy", "topic": "Inflation", "difficulty": "Medium"}, {"id": 6, "subject": "Economy", "topic": "Balance of Payments", "difficulty": "Medium"}, {"id": 7, "subject": "Economy", "topic": "General Economic Concepts", "difficulty": "Easy"}, {"id": 8, "subject": "Economy", "topic": "National Income Accounting", "difficulty": "Medium"}, {"id": 9, "subject": "Economy", "topic": "Monetary and Fiscal Policy", "difficulty": "Medium"}, {"id": 10, "subject": "Economy", "topic": "International Trade", "difficulty": "Medium"}, {"id": 11, "subject": "Economy", "topic": "Energy Sector", "difficulty": "Medium"}, {"id": 12, "subject": "Economy", "topic": "Industrial Policy", "difficulty": "Medium"}, {"id": 13, "subject": "Economy", "topic": "Money Supply", "difficulty": "Medium"}, {"id": 14, "subject": "Economy", "topic": "Ease of Doing Business", "difficulty": "Medium"}, {"id": 15, "subject": "Economy", "topic": "Taxation (GST)", "difficulty": "Medium"}, {"id": 16, "subject": "Economy", "topic": "Macroeconomic Stability", "difficulty": "Medium"}, {"id": 17, "subject": "Social Issues", "topic": "Poverty", "difficulty": "Medium"}, {"id": 18, "subject": "Economy", "topic": "Macroeconomic Stability", "difficulty": "Medium"}, {"id": 19, "subject": "Economy", "topic": "Monetary Policy", "difficulty": "Medium"}, {"id": 20, "subject": "Economy", "topic": "Monetary Policy", "difficulty": "Medium"}, {"id": 21, "subject": "Economy", "topic": "Agriculture", "difficulty": "Medium"}, {"id": 22, "subject": "Economy", "topic": "Food Security", "difficulty": "Easy"}, {"id": 23, "subject": "Social Issues", "topic": "Rural Development", "difficulty": "Easy"}, {"id": 24, "subject": "Economy", "topic": "Economic Growth (Andhra Pradesh)", "difficulty": "Medium"}, {"id": 25, "subject": "Economy", "topic": "Per Capita Income (India & AP)", "difficulty": "Medium"}, {"id": 26, "subject": "Economy", "topic": "Agriculture (Andhra Pradesh)", "difficulty": "Medium"}, {"id": 27, "subject": "Social Issues", "topic": "Rural Development (Andhra Pradesh)", "difficulty": "Medium"}, {"id": 28, "subject": "Economy", "topic": "Economic Growth (Andhra Pradesh)", "difficulty": "Medium"}, {"id": 29, "subject": "Economy", "topic": "Economic Performance (Indian States)", "difficulty": "Medium"}, {"id": 30, "subject": "Economy", "topic": "Public Finance (Andhra Pradesh)", "difficulty": "Medium"}]