[
  {
    "q_num": 1,
    "question": "ప్రతి ప్రశ్నకి 150 ప్రశ్నలున్నవి, ప్రతి ప్రశ్నకు 1 మార్కు కేటాయించబడినది. ప్రతి తప్పు సమాధానానికి 1/3 మార్కు తీసివేయడం జరుగుతుంది.",
    "options": {
      "1": null,
      "2": null,
      "3": null,
      "4": null
    },
    "correct": null,
    "has_image": false,
    "needs_review": true
  },
  {
    "q_num": 2,
    "question": "ప్రశ్న పత్రం ఇంగ్లీషులో తయారుచేయబడి తెలుగు భాషలోకి అనువదించబడినది. సమాధాన పత్రం మదింపు చేయునప్పుడు ఇంగ్లీషు ప్రశ్న పత్రం ప్రామాణికముగా తీసుకోబడును.",
    "options": {
      "1": null,
      "2": null,
      "3": null,
      "4": null
    },
    "correct": null,
    "has_image": false,
    "needs_review": true
  },
  {
    "q_num": 3,
    "question": "ప్రశ్న పత్రములో అన్ని ప్రశ్నలు ముఖ్యమైనవి. ప్రతి ప్రశ్నలో గాని, OMR సమాధాన పత్రములో గాని తప్పు లోపమున్నచో దాని సాధనముతోనే చేరకానించి వెంటనే తీసివేయవలెను. OMR సమాధాన పత్రములో రెండు కాపీలు కలవు. వాటిని నింపరాదు. మొదట కాపీలో నీలిగూరలు రెండవ కాపీలో కూడా మార్పులు, మొదట కాపీ (ఒరిజినల్) మార్పులకు కంసం పంపబడును మరియు తిరిగి ఇవ్వబడును.",
    "options": {
      "1": null,
      "2": null,
      "3": null,
      "4": null
    },
    "correct": null,
    "has_image": false,
    "needs_review": true
  },
  {
    "q_num": 4,
    "question": "మీ యొక్క Registered Number ప్రశ్న పత్రము బ భాగములో వ్రాయవలెను. మొదట నీటి కుడివైపు పై భాగములో ప్రశ్న పత్రము యొక్క వర్గము (A) అని గాని B అని గాని C అని గాని D అని గాని ముద్రించబడినది. OMR సమాధాన పత్రము ఒకటవ (Side-1) కుడివైపు పై భాగములో పార్ట్ C నందు ప్రశ్నపత్రము యొక్క వర్గము A, B, C, D లు ముద్రించబడినవి. మీ ప్రశ్న పత్రము యొక్క వర్గమును, సమాధాన పత్రములో నింపవలెను. మీ ప్రశ్న పత్రము యొక్క వర్గమును, సమాధాన పత్రములో సరియగునట్లుగా నింపవలెను. OMR సమాధాన పత్రంలో ప్రశ్న పత్రము యొక్క వర్గమును నింపవలెను : మీ ప్రశ్న పత్రము యొక్క వర్గము A అయినచో, ఈ క్రింద చూపిన విధంగా నింపవలెను. మీ ప్రశ్న పత్రము యొక్క వర్గమును (Series), సమాధాన పత్రము ఒకటవ పార్ట్ C లో బ్లూ/బ్లాక్ బాల్‌పాయింట్ పెన్నుతో రుద్దకుండా లేదా లేత రంగు పత్రము ఖచ్చితంగా తెలుసుకొనుటకు వీలు లేకుండా ఉండునట్లు, మీకు నిలువుగా ఉన్నట్లుగా సరిగా నింపవలెను. దీనికి విలువ ఉండదు.",
    "options": {
      "1": null,
      "2": null,
      "3": null,
      "4": null
    },
    "correct": null,
    "has_image": false,
    "needs_review": true
  }
]